dash_recording_components/AudioRecorder.py
dash_recording_components/__init__.py
dash_recording_components/_imports_.py
dash_recording_components/dash_recording_components.dev.js
dash_recording_components/dash_recording_components.min.js
dash_recording_components/dash_recording_components.min.js.LICENSE.txt
dash_recording_components/metadata.json
dash_recording_components/package.json
dash_recording_components-1.0.3.dist-info/METADATA
dash_recording_components-1.0.3.dist-info/WHEEL
dash_recording_components-1.0.3.dist-info/RECORD
