Metadata-Version: 2.1
Name: dash-recording-components
Version: 1.0.3
Summary: A Dash component for recording audio from the browser
Home-page: https://github.com/danielenricocahall/dash-recording-components
License: MIT
Author: Daniel Cahall
Author-email: danielenricocahall@gmail.com
Requires-Python: >=3.8,<3.12
Classifier: License :: OSI Approved :: MIT License
Classifier: Programming Language :: Python :: 3
Classifier: Programming Language :: Python :: 3.8
Classifier: Programming Language :: Python :: 3.9
Classifier: Programming Language :: Python :: 3.10
Classifier: Programming Language :: Python :: 3.11
Requires-Dist: dash (>=2.14.1,<3.0.0)
